MANIFEST.in
README.rst
setup.py
aio/__init__.py
aio.web.page.egg-info/PKG-INFO
aio.web.page.egg-info/SOURCES.txt
aio.web.page.egg-info/dependency_links.txt
aio.web.page.egg-info/namespace_packages.txt
aio.web.page.egg-info/not-zip-safe
aio.web.page.egg-info/requires.txt
aio.web.page.egg-info/top_level.txt
aio/web/__init__.py
aio/web/page/README.rst
aio/web/page/__init__.py
aio/web/page/fragments.py
aio/web/page/routes.py
aio/web/page/templates/base.html
aio/web/page/templates/footer.html
aio/web/page/templates/header.html
aio/web/page/testing/__init__.py
aio/web/page/tests/__init__.py
aio/web/page/tests/templates/test_template.html
aio/web/page/tests/templates/fragments/test_fragment.html